stdeb3/__init__.py
stdeb3/cli_runner.py
stdeb3/downloader.py
stdeb3/transport.py
stdeb3/util.py
stdeb3/command/__init__.py
stdeb3/command/bdist_deb.py
stdeb3/command/common.py
stdeb3/command/debianize.py
stdeb3/command/install_deb.py
stdeb3/command/sdist_dsc.py
stdeb3-0.9.0.post2.data/scripts/py2dsc
stdeb3-0.9.0.post2.data/scripts/py2dsc-deb
stdeb3-0.9.0.post2.data/scripts/pypi-download
stdeb3-0.9.0.post2.data/scripts/pypi-install
stdeb3-0.9.0.post2.dist-info/DESCRIPTION.rst
stdeb3-0.9.0.post2.dist-info/METADATA
stdeb3-0.9.0.post2.dist-info/RECORD
stdeb3-0.9.0.post2.dist-info/WHEEL
stdeb3-0.9.0.post2.dist-info/metadata.json
stdeb3-0.9.0.post2.dist-info/top_level.txt
